{
"3_lIlw": {
"checksum": "8fc9aa94e895058987dc5c2e31989346",
"date": 1393928095.0,
"description": "<div class=\"markdown\"><p>Une liste des arguments rhetologiques fallacieux</p></div>\n\n<br />&#8212; <a href=\"https:/shaare/x-svpQ\" title=\"Permalink\">Permalink</a>",
"docolav": "9E8A9A",
"file": "3_lIlw.png",
"guid": "https:/shaare/x-svpQ",
"height": 6858,
"tags": [
"argument",
"bad"
],
"title": "1276_rhetological_fallacies_FR.png (1276\u00d76858)",
"url": "http://www.nikopik.com/wp-content/uploads/2013/09/1276_rhetological_fallacies_FR.png",
"width": 1276
}
}