{
"4G1-BA": {
"checksum": "eb79b835abd877d95d1120dfbe66a2ca",
"date": 1509336532.0,
"description": "(<a href=\"https://shaarli.zertrin.org/?vo30uQ\">Permalink</a>)",
"docolav": "C0D6CB",
"file": "4G1-BA.jpg",
"guid": "https://shaarli.zertrin.org/?vo30uQ",
"height": 2786,
"tags": [],
"title": "A movie junkie listed more than 1,800 must-see movies and arranged them by genre and themes on a giant imaginary roadmap",
"url": "https://i.redd.it/jmqqav1dmuuz.jpg",
"width": 4180
},
"Avjbhw": {
"checksum": "5baf1bab9f2285b4d9df6e9a959411e9",
"date": 1405478563.0,
"description": "Flowchart to solve common problems when something was done wrong in git.<br />(<a href=\"https://shaarli.zertrin.org/?hJR1zg\">Permalink</a>)",
"docolav": "EAEAE8",
"file": "Avjbhw.png",
"guid": "https://shaarli.zertrin.org/?hJR1zg",
"height": 1677,
"tags": [
"dev",
"flowchart",
"git",
"pretty",
"programming"
],
"title": "Git pretty - So you have a mess on your hands",
"url": "http://justinhileman.info/article/git-pretty/git-pretty.png",
"width": 1692
},
"TlXgQw": {
"checksum": "0b347397659f5ac6e798d7a897cc9232",
"date": 1352741881.0,
"description": "(<a href=\"https://shaarli.zertrin.org/?z79dFw\">Permalink</a>)",
"docolav": "F8F8F8",
"file": "TlXgQw.png",
"guid": "https://shaarli.zertrin.org/?z79dFw",
"height": 848,
"tags": [
"authentification",
"certificate",
"security",
"ssl",
"threat-model"
],
"title": "SSL Threat Model",
"url": "http://blog.ivanristic.com/SSL_Threat_Model.png",
"width": 1491
},
"hO_kUg": {
"checksum": "4bf487b0487acf3ccd18e48d8f86a489",
"date": 1383050833.0,
"description": "From WTFViz, but still interesting.<br />(<a href=\"https://shaarli.zertrin.org/?ECG-Ug\">Permalink</a>)",
"docolav": "EFEEED",
"file": "hO_kUg.jpg",
"guid": "https://shaarli.zertrin.org/?ECG-Ug",
"height": 2160,
"tags": [
"best",
"film",
"map",
"movie",
"wtf"
],
"title": "The best movies of all time map",
"url": "http://macguffin007.files.wordpress.com/2013/09/250-best-movies-map.jpg",
"width": 3507
},
"kNn0Ew": {
"checksum": "dd64ebce10c031b0a31242f99eeac2b2",
"date": 1384679446.0,
"description": "Et si les Alpes \u00e9taient un archipel.<br />\n<br />\n(via <a href=\"http://seenthis.net/messages/197174\">http://seenthis.net/messages/197174</a>)<br />(<a href=\"https://shaarli.zertrin.org/?-k6XOg\">Permalink</a>)",
"docolav": "5480C1",
"file": "kNn0Ew.png",
"guid": "https://shaarli.zertrin.org/?-k6XOg",
"height": 925,
"tags": [
"alpes",
"archipel",
"carte",
"cartographie",
"mer",
"montagne",
"visualisation"
],
"title": "Archipel alpin",
"url": "http://i.imgur.com/77lksAy.png",
"width": 1309
},
"we405g": {
"checksum": "b9c80c84fcbb9c18ac259e3e0fc63fdc",
"date": 1380955883.0,
"description": "(<a href=\"https://shaarli.zertrin.org/?t2Ftqw\">Permalink</a>)",
"docolav": "838593",
"file": "we405g.jpg",
"guid": "https://shaarli.zertrin.org/?t2Ftqw",
"height": 1463,
"tags": [
"auto",
"voiture",
"volkswagen",
"vw"
],
"title": "Une Volkswagen d\u00e9mont\u00e9e enti\u00e8rement",
"url": "http://i.imgur.com/nQwc6YM.jpg",
"width": 2870
}
}